perso/vcs/__init__.py
perso/vcs/__main__.py
perso/vcs/exceptions.py
perso/vcs/hashing/__init__.py
perso/vcs/hashing/exceptions.py
perso/vcs/main.py
perso/vcs/metadata.py
perso/vcs/package.py
perso/vcs/settings.py
perso_vcs-0.0.0a0.dist-info/WHEEL
perso_vcs-0.0.0a0.dist-info/METADATA
perso_vcs-0.0.0a0.dist-info/RECORD
